pureai_chunk/RagPUREAI_chuncks_clean.cpython-311-x86_64-linux-gnu.so
pureai_chunk/__init__.py
pureai_chunk-0.0.1.dist-info/METADATA
pureai_chunk-0.0.1.dist-info/WHEEL
pureai_chunk-0.0.1.dist-info/top_level.txt
pureai_chunk-0.0.1.dist-info/RECORD
